genai_prices/__init__.py
genai_prices/__main__.py
genai_prices/_cli.py
genai_prices/data.py
genai_prices/data_snapshot.py
genai_prices/py.typed
genai_prices/types.py
genai_prices/update_prices.py
genai_prices-0.0.50.dist-info/licenses/LICENSE
genai_prices-0.0.50.dist-info/WHEEL
genai_prices-0.0.50.dist-info/entry_points.txt
genai_prices-0.0.50.dist-info/METADATA
genai_prices-0.0.50.dist-info/RECORD
