Metadata-Version: 2.4
Name: genai-prices
Version: 0.0.50
Summary: Calculate prices for calling LLM inference APIs.
Author: Samuel Colvin
Author-email: Samuel Colvin <samuel@pydantic.dev>
License-Expression: MIT
License-File: LICENSE
Classifier: Development Status :: 4 - Beta
Classifier: Programming Language :: Python
Classifier: Programming Language :: Python :: 3
Classifier: Programming Language :: Python :: 3 :: Only
Classifier: Programming Language :: Python :: 3.9
Classifier: Programming Language :: Python :: 3.10
Classifier: Programming Language :: Python :: 3.11
Classifier: Programming Language :: Python :: 3.12
Classifier: Programming Language :: Python :: 3.13
Classifier: Intended Audience :: Developers
Classifier: Intended Audience :: Information Technology
Classifier: Intended Audience :: System Administrators
Classifier: License :: OSI Approved :: MIT License
Classifier: Operating System :: Unix
Classifier: Operating System :: POSIX :: Linux
Classifier: Environment :: Console
Classifier: Environment :: MacOS X
Classifier: Topic :: Software Development :: Libraries :: Python Modules
Classifier: Topic :: Internet
Requires-Dist: eval-type-backport>=0.2 ; python_full_version < '3.10'
Requires-Dist: httpx>=0.27
Requires-Dist: pydantic>=2.10
Requires-Python: >=3.9
Project-URL: Changelog, https://github.com/pydantic/genai-prices/releases
Project-URL: Homepage, https://github.com/pydantic/genai-prices
Project-URL: Source, https://github.com/pydantic/genai-prices
